cli/__init__.py
cli/rooctl.py
rooctl-1.0.1.dist-info/licenses/LICENSE
rooctl-1.0.1.dist-info/METADATA
rooctl-1.0.1.dist-info/WHEEL
rooctl-1.0.1.dist-info/entry_points.txt
rooctl-1.0.1.dist-info/top_level.txt
rooctl-1.0.1.dist-info/RECORD
