Metadata-Version: 2.4
Name: rooctl
Version: 1.0.1
Summary: Official CLI for FounderX-AI Orchestration System - Execute templates, manage artifacts, and monitor workflows from the command line
Author-email: FounderX-AI <dev@founder-x.ai>
Maintainer-email: FounderX-AI <dev@founder-x.ai>
License-Expression: MIT
Project-URL: Homepage, https://github.com/founderx-ai/RooCommands
Project-URL: Documentation, https://docs.founder-x.ai/cli
Project-URL: Source Code, https://github.com/founderx-ai/RooCommands/tree/main/orchestration-system/cli
Project-URL: Bug Tracker, https://github.com/founderx-ai/RooCommands/issues
Keywords: orchestration,cli,founderx,automation,workflow,command-line,founderx-ai
Classifier: Development Status :: 4 - Beta
Classifier: Intended Audience :: Developers
Classifier: Topic :: Software Development :: Build Tools
Classifier: Programming Language :: Python :: 3
Classifier: Programming Language :: Python :: 3.9
Classifier: Programming Language :: Python :: 3.10
Classifier: Programming Language :: Python :: 3.11
Classifier: Programming Language :: Python :: 3.12
Requires-Python: >=3.9
License-File: LICENSE
Requires-Dist: rc-orchestration-sdk>=1.1.1
Requires-Dist: click>=8.0.0
Requires-Dist: rich>=13.0.0
Requires-Dist: tabulate>=0.9.0
Dynamic: license-file
